<?xml version="1.0" encoding="utf-8"?>
<ModMetaData>
<name>Roo's Minotaur Xenotype Expanded</name>
<author>Rooboid, Zelan</author>
<supportedVersions>
		<li>1.4</li>
</supportedVersions>
<packageId>Rooboid.Minotaur.Expanded</packageId>
	<loadAfter>
		<li>Ludeon.RimWorld</li>
		<li>Ludeon.RimWorld.Royalty</li>
		<li>Ludeon.RimWorld.Ideology</li>
		<li>Ludeon.RimWorld.Biotech</li>
		<li>OskarPotocki.VanillaFactionsExpanded.Core</li>
		<li>VanillaExpanded.VanillaTraitsExpanded</li>
		<li>Rooboid.Minotaur</li>
		<li>fuglypump.fallouttraits</li>
		<li>odysseylotus.seren</li>
	</loadAfter>
		<modDependencies>
		<li>
			<packageId>brrainz.harmony</packageId>
			<displayName>Harmony</displayName>
			<downloadUrl>https://github.com/pardeike/HarmonyRimWorld</downloadUrl>
			<steamWorkshopUrl>https://steamcommunity.com/sharedfiles/filedetails/?id=2009463077</steamWorkshopUrl>
		</li>
		<li>
			<packageId>Rooboid.Minotaur</packageId>
			<displayName>Roo's Minotaur Xenotype</displayName>
			<downloadUrl>https://steamcommunity.com/id/rooboid/myworkshopfiles/</downloadUrl>
			<steamWorkshopUrl>https://steamcommunity.com/id/rooboid/myworkshopfiles/</steamWorkshopUrl>
		</li>
		<li>
			<packageId>Ludeon.RimWorld.Biotech</packageId>
			<displayName>Biotech</displayName>
			<downloadUrl>https://store.steampowered.com/app/1826140/RimWorld__Biotech/?curator_clanid=25160263</downloadUrl>
			<steamWorkshopUrl>https://store.steampowered.com/app/1826140/RimWorld__Biotech/?curator_clanid=25160263</steamWorkshopUrl>
		</li>
	</modDependencies>
<description>Welcome the minotaur to the Rim with open arms with this expanded module of Roo's Minotaur Xenotype. Battle or befriend multiple minotaur factions, build your own army of bovine hoplites and flesh out your pawns with brand new backstories and apparel.

This mod must be loaded after the core module: Roo's Minotaur Xenotype

&lt;size=25&gt;• Features&lt;/size&gt;

• 35+ minotaur related backstories.
• 25 high-quality hairstyles.
• 3 brand new and exciting starting scenarios.
• 5+ pieces of apparel and weaponry.
• 2 minotaur factions with unique raids and pawn types.
• Various DLC add-ons such as custom ideology icons and cultures.
• Integrated compatibility with various great mods.

&lt;size=25&gt;• Credits&lt;/size&gt;

&lt;size=20&gt;Mod:&lt;/size&gt;
• Graphics and XML: Rooboid
• C# and emotional support: Zelan

&lt;size=20&gt;Patreon:&lt;/size&gt;
Lambvey, Mangulwort, panatakan yen, Alexandre, Galen, Only, Greg Bunger, D-Train, 1Sopel6, WoolyPie, Dodo, Josh and Prince</description>
</ModMetaData>